evohome_rf/__init__.py
evohome_rf/address.py
evohome_rf/command.py
evohome_rf/const.py
evohome_rf/devices.py
evohome_rf/discovery.py
evohome_rf/exceptions.py
evohome_rf/helpers.py
evohome_rf/message.py
evohome_rf/opentherm.py
evohome_rf/packet.py
evohome_rf/parsers.py
evohome_rf/protocol.py
evohome_rf/ramses.py
evohome_rf/schema.py
evohome_rf/systems.py
evohome_rf/transport.py
evohome_rf/version.py
evohome_rf/zones.py
evohome_rf-0.8.6.dist-info/LICENSE
evohome_rf-0.8.6.dist-info/METADATA
evohome_rf-0.8.6.dist-info/WHEEL
evohome_rf-0.8.6.dist-info/top_level.txt
evohome_rf-0.8.6.dist-info/RECORD
