Metadata-Version: 2.1
Name: evohome-rf
Version: 0.8.6
Summary: An interface for Honeywell RF (RAMSES II), as used by HVAC, CH/DHW.
Home-page: https://github.com/zxdavb/evohome_rf
Author: David Bonnes
Author-email: zxdavb@gmail.com
License: MIT
Download-URL: https://github.com/zxdavb/evohome_rf/archive/0.8.6.tar.gz
Keywords: ramses,evohome,sunidal,chronotherm,hometronics
Platform: UNKNOWN
Classifier: Development Status :: 3 - Alpha
Classifier: License :: OSI Approved :: MIT License
Classifier: Operating System :: OS Independent
Classifier: Programming Language :: Python :: 3.7
Classifier: Topic :: Home Automation
Requires-Python: >=3.7
Requires-Dist: colorlog (>=4.7.2)
Requires-Dist: pyserial-asyncio (>=0.5)
Requires-Dist: voluptuous (>=0.12.1)
